yapsygui/__init__.py
yapsygui/__main__.py
yapsygui/dialog.py
yapsygui/endpoint.py
yapsygui/items.py
yapsygui/manager.py
yapsygui/network_request.py
yapsygui/plugin_action.py
yapsygui/plugin_network.py
yapsygui/template.html
yapsygui/template.py
yapsygui/utils.py
yapsygui/plugins/plugin1.plugin
yapsygui/plugins/plugin1.py
yapsygui/ui/__init__.py
yapsygui/ui/alert.py
yapsygui/ui/dialog_plugin_base.py
yapsygui/ui/open_file.py
yapsygui/ui/panel_description.py
yapsygui/ui/panel_plugins.py
yapsygui/ui/row_buttons.py
yapsygui/ui/twin_panel.py
yapsygui-1.1.4.dist-info/LICENSE
yapsygui-1.1.4.dist-info/METADATA
yapsygui-1.1.4.dist-info/WHEEL
yapsygui-1.1.4.dist-info/entry_points.txt
yapsygui-1.1.4.dist-info/top_level.txt
yapsygui-1.1.4.dist-info/RECORD
