Metadata-Version: 2.1
Name: yapsygui
Version: 1.1.4
Summary: GUI for Yapsy plugin system
Home-page: https://github.com/leonelhs/yapsy-gui
Author: leonel hernandez
Author-email: leonelhs@gmail.com
License: Apache
Classifier: Development Status :: 5 - Production/Stable
Classifier: Intended Audience :: Developers
Classifier: Intended Audience :: Science/Research
Classifier: Natural Language :: English
Classifier: Operating System :: OS Independent
Classifier: Programming Language :: Python
Classifier: Programming Language :: Python :: 3.5
Classifier: Programming Language :: Python :: 3.6
Classifier: Programming Language :: Python :: 3.7
Classifier: Programming Language :: Python :: 3.8
Classifier: Programming Language :: Python :: 3.9
Classifier: Programming Language :: Python :: 3 :: Only
License-File: LICENSE
Requires-Dist: yapsy (>=1.12.2)
Requires-Dist: qtpy (>=1.11.2)
